Metadata-Version: 1.1
Name: funniest-from-sajjad
Version: 0.1
Summary: The funniest joke in the world
Home-page: http://github.com/storborg/funniest
Author: sajjad alizadeh
Author-email: sajjad.yazd@gmail.com
License: MIT
Keywords: funniest joke comedy flying circus
Platform: UNKNOWN
Classifier: Development Status :: 3 - Alpha
Classifier: License :: OSI Approved :: MIT License
Classifier: Programming Language :: Python :: 2.7
Classifier: Topic :: Text Processing :: Linguistic
